[
    {
        "avatar": "https://avatars.githubusercontent.com/u/661450",
        "name": "Arvid Norberg",
        "repo": {
            "description": "an efficient feature complete C++ bittorrent implementation",
            "name": "libtorrent",
            "url": "https://github.com/arvidn/libtorrent"
        },
        "sponsorUrl": "https://github.com/sponsors/arvidn",
        "url": "https://github.com/arvidn",
        "username": "arvidn"
    },
    {
        "avatar": "https://avatars.githubusercontent.com/u/245435",
        "name": "Carlos Alexandro Becker",
        "repo": {
            "description": "Exports the expiration time of your domains as prometheus metrics.",
            "name": "domain_exporter",
            "url": "https://github.com/caarlos0/domain_exporter"
        },
        "sponsorUrl": "https://github.com/sponsors/caarlos0",
        "url": "https://github.com/caarlos0",
        "username": "caarlos0"
    },
    {
        "avatar": "https://avatars.githubusercontent.com/u/195327",
        "name": "Franck Nijhof",
        "repo": {
            "description": "A curated list of amazingly awesome Home Assistant resources.",
            "name": "awesome-home-assistant",
            "url": "https://github.com/frenck/awesome-home-assistant"
        },
        "sponsorUrl": "https://github.com/sponsors/frenck",
        "url": "https://github.com/frenck",
        "username": "frenck"
    },
    {
        "avatar": "https://avatars.githubusercontent.com/u/1810591",
        "name": "Anthony Sottile",
        "repo": {
            "description": "A tool (and pre-commit hook) to automatically upgrade syntax for newer versions of the language.",
            "name": "pyupgrade",
            "url": "https://github.com/asottile/pyupgrade"
        },
        "sponsorUrl": "https://github.com/sponsors/asottile",
        "url": "https://github.com/asottile",
        "username": "asottile"
    },
    {
        "avatar": "https://avatars.githubusercontent.com/u/928116",
        "name": "Michele Locati",
        "repo": {
            "description": "Easily install PHP extension in Docker containers",
            "name": "docker-php-extension-installer",
            "url": "https://github.com/mlocati/docker-php-extension-installer"
        },
        "sponsorUrl": "https://github.com/sponsors/mlocati",
        "url": "https://github.com/mlocati",
        "username": "mlocati"
    },
    {
        "avatar": "https://avatars.githubusercontent.com/u/72989",
        "name": "kazuya kawaguchi",
        "repo": {
            "description": "\ud83c\udf10 Internationalization plugin for Vue.js",
            "name": "vue-i18n",
            "url": "https://github.com/kazupon/vue-i18n"
        },
        "sponsorUrl": "https://github.com/sponsors/kazupon",
        "url": "https://github.com/kazupon",
        "username": "kazupon"
    },
    {
        "avatar": "https://avatars.githubusercontent.com/u/5425387",
        "name": "Ben V. Brown",
        "repo": {
            "description": "Open Source Soldering Iron firmware for Miniware and Pinecil",
            "name": "IronOS",
            "url": "https://github.com/Ralim/IronOS"
        },
        "sponsorUrl": null,
        "url": "https://github.com/Ralim",
        "username": "Ralim"
    },
    {
        "avatar": "https://avatars.githubusercontent.com/u/15646325",
        "name": "Visiky",
        "repo": {
            "description": "\ud83d\ude80 \u5728\u7ebf\u7b80\u5386\u751f\u6210\u5668",
            "name": "resume",
            "url": "https://github.com/visiky/resume"
        },
        "sponsorUrl": null,
        "url": "https://github.com/visiky",
        "username": "visiky"
    },
    {
        "avatar": "https://avatars.githubusercontent.com/u/10513364",
        "name": "Bill",
        "repo": {
            "description": "\ud83c\udfaf React UI animation made easy",
            "name": "react-simple-animate",
            "url": "https://github.com/bluebill1049/react-simple-animate"
        },
        "sponsorUrl": "https://github.com/sponsors/bluebill1049",
        "url": "https://github.com/bluebill1049",
        "username": "bluebill1049"
    },
    {
        "avatar": "https://avatars.githubusercontent.com/u/16143594",
        "name": "Lennart",
        "repo": {
            "description": "Get high-quality and customizable Gatsby themes to quickly bootstrap your website! Choose from many professionally created and impressive designs with a wide variety of features and customization options.",
            "name": "gatsby-themes",
            "url": "https://github.com/LekoArts/gatsby-themes"
        },
        "sponsorUrl": "https://github.com/sponsors/LekoArts",
        "url": "https://github.com/LekoArts",
        "username": "LekoArts"
    },
    {
        "avatar": "https://avatars.githubusercontent.com/u/2008794",
        "name": "John Kerl",
        "repo": {
            "description": "Miller is like awk, sed, cut, join, and sort for name-indexed data such as CSV, TSV, and tabular JSON",
            "name": "miller",
            "url": "https://github.com/johnkerl/miller"
        },
        "sponsorUrl": null,
        "url": "https://github.com/johnkerl",
        "username": "johnkerl"
    },
    {
        "avatar": "https://avatars.githubusercontent.com/u/663378",
        "name": "Juliette",
        "repo": null,
        "sponsorUrl": null,
        "url": "https://github.com/jrfnl",
        "username": "jrfnl"
    },
    {
        "avatar": "https://avatars.githubusercontent.com/u/1951866",
        "name": "CrazyMax",
        "repo": {
            "description": "Block spying and tracking on Windows",
            "name": "WindowsSpyBlocker",
            "url": "https://github.com/crazy-max/WindowsSpyBlocker"
        },
        "sponsorUrl": "https://github.com/sponsors/crazy-max",
        "url": "https://github.com/crazy-max",
        "username": "crazy-max"
    },
    {
        "avatar": "https://avatars.githubusercontent.com/u/522948",
        "name": "Justin Fagnani",
        "repo": {
            "description": "A simple expression parser and evaluator for JavaScript",
            "name": "jexpr",
            "url": "https://github.com/justinfagnani/jexpr"
        },
        "sponsorUrl": null,
        "url": "https://github.com/justinfagnani",
        "username": "justinfagnani"
    },
    {
        "avatar": "https://avatars.githubusercontent.com/u/218610",
        "name": "Trask Stalnaker",
        "repo": null,
        "sponsorUrl": null,
        "url": "https://github.com/trask",
        "username": "trask"
    },
    {
        "avatar": "https://avatars.githubusercontent.com/u/8851",
        "name": "R. Bernstein",
        "repo": {
            "description": "A cross-version Python bytecode decompiler",
            "name": "python-uncompyle6",
            "url": "https://github.com/rocky/python-uncompyle6"
        },
        "sponsorUrl": "https://github.com/sponsors/rocky",
        "url": "https://github.com/rocky",
        "username": "rocky"
    },
    {
        "avatar": "https://avatars.githubusercontent.com/u/220358",
        "name": "Andrew Kane",
        "repo": {
            "description": "A performance dashboard for Postgres",
            "name": "pghero",
            "url": "https://github.com/ankane/pghero"
        },
        "sponsorUrl": null,
        "url": "https://github.com/ankane",
        "username": "ankane"
    },
    {
        "avatar": "https://avatars.githubusercontent.com/u/1329033",
        "name": "Jakub",
        "repo": {
            "description": "Better video player for Flutter, with multiple configuration options. Solving typical use cases!",
            "name": "betterplayer",
            "url": "https://github.com/jhomlala/betterplayer"
        },
        "sponsorUrl": null,
        "url": "https://github.com/jhomlala",
        "username": "jhomlala"
    },
    {
        "avatar": "https://avatars.githubusercontent.com/u/456674",
        "name": "Andrew Gallant",
        "repo": {
            "description": "ripgrep recursively searches directories for a regex pattern while respecting your gitignore",
            "name": "ripgrep",
            "url": "https://github.com/BurntSushi/ripgrep"
        },
        "sponsorUrl": null,
        "url": "https://github.com/BurntSushi",
        "username": "BurntSushi"
    },
    {
        "avatar": "https://avatars.githubusercontent.com/u/2892853",
        "name": "Koen Kanters",
        "repo": {
            "description": "Zigbee \ud83d\udc1d to MQTT bridge \ud83c\udf09, get rid of your proprietary Zigbee bridges \ud83d\udd28",
            "name": "zigbee2mqtt",
            "url": "https://github.com/Koenkk/zigbee2mqtt"
        },
        "sponsorUrl": "https://github.com/sponsors/Koenkk",
        "url": "https://github.com/Koenkk",
        "username": "Koenkk"
    },
    {
        "avatar": "https://avatars.githubusercontent.com/u/5047891",
        "name": "Alexandru Dima",
        "repo": null,
        "sponsorUrl": null,
        "url": "https://github.com/alexdima",
        "username": "alexdima"
    },
    {
        "avatar": "https://avatars.githubusercontent.com/u/12689835",
        "name": "Bo Zhang",
        "repo": {
            "description": "\u4e3aWebx\u521d\u5b66\u8005\u63d0\u4f9b\u7684\u6587\u6863\u3002",
            "name": "webx_beginner_guide",
            "url": "https://github.com/blindpirate/webx_beginner_guide"
        },
        "sponsorUrl": null,
        "url": "https://github.com/blindpirate",
        "username": "blindpirate"
    },
    {
        "avatar": "https://avatars.githubusercontent.com/u/2851492",
        "name": "Florian Roth",
        "repo": {
            "description": "Best Practice Auditd Configuration",
            "name": "auditd",
            "url": "https://github.com/Neo23x0/auditd"
        },
        "sponsorUrl": null,
        "url": "https://github.com/Neo23x0",
        "username": "Neo23x0"
    },
    {
        "avatar": "https://avatars.githubusercontent.com/u/6212603",
        "name": "Asif Saif Uddin",
        "repo": null,
        "sponsorUrl": null,
        "url": "https://github.com/auvipy",
        "username": "auvipy"
    },
    {
        "avatar": "https://avatars.githubusercontent.com/u/1478487",
        "name": "Marten Seemann",
        "repo": null,
        "sponsorUrl": null,
        "url": "https://github.com/marten-seemann",
        "username": "marten-seemann"
    }
]