[
    {
        "avatar": "https://avatars.githubusercontent.com/u/34928425",
        "name": "Paco",
        "repo": {
            "description": "Fast, unstyled command menu React component.",
            "name": "cmdk",
            "url": "https://github.com/pacocoursey/cmdk"
        },
        "sponsorUrl": null,
        "url": "https://github.com/pacocoursey",
        "username": "pacocoursey"
    },
    {
        "avatar": "https://avatars.githubusercontent.com/u/4196",
        "name": "Hadley Wickham",
        "repo": {
            "description": "R for data science: a book",
            "name": "r4ds",
            "url": "https://github.com/hadley/r4ds"
        },
        "sponsorUrl": null,
        "url": "https://github.com/hadley",
        "username": "hadley"
    },
    {
        "avatar": "https://avatars.githubusercontent.com/u/45696119",
        "name": "Bruno D'Luka",
        "repo": {
            "description": "Implements Microsoft's Fluent Design System in Flutter.",
            "name": "fluent_ui",
            "url": "https://github.com/bdlukaa/fluent_ui"
        },
        "sponsorUrl": null,
        "url": "https://github.com/bdlukaa",
        "username": "bdlukaa"
    },
    {
        "avatar": "https://avatars.githubusercontent.com/u/408570",
        "name": "Seth Vargo",
        "repo": {
            "description": "A Go library for parsing struct tags from environment variables.",
            "name": "go-envconfig",
            "url": "https://github.com/sethvargo/go-envconfig"
        },
        "sponsorUrl": null,
        "url": "https://github.com/sethvargo",
        "username": "sethvargo"
    },
    {
        "avatar": "https://avatars.githubusercontent.com/u/218610",
        "name": "Trask Stalnaker",
        "repo": null,
        "sponsorUrl": null,
        "url": "https://github.com/trask",
        "username": "trask"
    },
    {
        "avatar": "https://avatars.githubusercontent.com/u/7009300",
        "name": "Iman khoshabi",
        "repo": {
            "description": "FL Chart is a highly customizable Flutter chart library that supports Line Chart, Bar Chart, Pie Chart, Scatter Chart, and Radar Chart.",
            "name": "fl_chart",
            "url": "https://github.com/imaNNeoFighT/fl_chart"
        },
        "sponsorUrl": null,
        "url": "https://github.com/imaNNeoFighT",
        "username": "imaNNeoFighT"
    },
    {
        "avatar": "https://avatars.githubusercontent.com/u/330628",
        "name": "Ralf Jung",
        "repo": {
            "description": "A precise specification for \"Rust lite / MIR plus\"",
            "name": "minirust",
            "url": "https://github.com/RalfJung/minirust"
        },
        "sponsorUrl": null,
        "url": "https://github.com/RalfJung",
        "username": "RalfJung"
    },
    {
        "avatar": "https://avatars.githubusercontent.com/u/9835",
        "name": "Peter Wagenet",
        "repo": null,
        "sponsorUrl": null,
        "url": "https://github.com/wagenet",
        "username": "wagenet"
    },
    {
        "avatar": "https://avatars.githubusercontent.com/u/315810",
        "name": "Michael Waskom",
        "repo": {
            "description": "Statistical data visualization in Python",
            "name": "seaborn",
            "url": "https://github.com/mwaskom/seaborn"
        },
        "sponsorUrl": null,
        "url": "https://github.com/mwaskom",
        "username": "mwaskom"
    },
    {
        "avatar": "https://avatars.githubusercontent.com/u/1560587",
        "name": "Jan-Otto Kr\u00f6pke",
        "repo": {
            "description": "A helm plugin that help manage secrets with Git workflow and store them anywhere",
            "name": "helm-secrets",
            "url": "https://github.com/jkroepke/helm-secrets"
        },
        "sponsorUrl": null,
        "url": "https://github.com/jkroepke",
        "username": "jkroepke"
    },
    {
        "avatar": "https://avatars.githubusercontent.com/u/173661",
        "name": "Alon Zakai",
        "repo": {
            "description": "Direct port of the Bullet physics engine to JavaScript using Emscripten",
            "name": "ammo.js",
            "url": "https://github.com/kripken/ammo.js"
        },
        "sponsorUrl": null,
        "url": "https://github.com/kripken",
        "username": "kripken"
    },
    {
        "avatar": "https://avatars.githubusercontent.com/u/71256",
        "name": "Nathan Rajlich",
        "repo": {
            "description": "A barebones WebSocket client and server implementation written in 100% Java.",
            "name": "Java-WebSocket",
            "url": "https://github.com/TooTallNate/Java-WebSocket"
        },
        "sponsorUrl": null,
        "url": "https://github.com/TooTallNate",
        "username": "TooTallNate"
    },
    {
        "avatar": "https://avatars.githubusercontent.com/u/5600341",
        "name": "Diego Muracciole",
        "repo": {
            "description": "\ud83d\udcc4 Create PDF files using React",
            "name": "react-pdf",
            "url": "https://github.com/diegomura/react-pdf"
        },
        "sponsorUrl": null,
        "url": "https://github.com/diegomura",
        "username": "diegomura"
    },
    {
        "avatar": "https://avatars.githubusercontent.com/u/8176128",
        "name": "Muntashir Al-Islam",
        "repo": {
            "description": "A full-featured package manager and viewer for Android",
            "name": "AppManager",
            "url": "https://github.com/MuntashirAkon/AppManager"
        },
        "sponsorUrl": null,
        "url": "https://github.com/MuntashirAkon",
        "username": "MuntashirAkon"
    },
    {
        "avatar": "https://avatars.githubusercontent.com/u/1090",
        "name": "Michael Klishin",
        "repo": {
            "description": "RabbitMQ HTTP API client in Go",
            "name": "rabbit-hole",
            "url": "https://github.com/michaelklishin/rabbit-hole"
        },
        "sponsorUrl": null,
        "url": "https://github.com/michaelklishin",
        "username": "michaelklishin"
    },
    {
        "avatar": "https://avatars.githubusercontent.com/u/2129",
        "name": "Jan-Erik Rediger",
        "repo": {
            "description": null,
            "name": "cargo-feature-set",
            "url": "https://github.com/badboy/cargo-feature-set"
        },
        "sponsorUrl": null,
        "url": "https://github.com/badboy",
        "username": "badboy"
    },
    {
        "avatar": "https://avatars.githubusercontent.com/u/1332805",
        "name": "Takuya Matsuyama",
        "repo": {
            "description": "My personal dotfiles",
            "name": "dotfiles-public",
            "url": "https://github.com/craftzdog/dotfiles-public"
        },
        "sponsorUrl": null,
        "url": "https://github.com/craftzdog",
        "username": "craftzdog"
    },
    {
        "avatar": "https://avatars.githubusercontent.com/u/227486",
        "name": "Chris Banes",
        "repo": {
            "description": "Tivi is a work-in-progress TV show tracking Android app, which connects to Trakt.tv. It is still in its early stages of development and c\u2026",
            "name": "tivi",
            "url": "https://github.com/chrisbanes/tivi"
        },
        "sponsorUrl": null,
        "url": "https://github.com/chrisbanes",
        "username": "chrisbanes"
    },
    {
        "avatar": "https://avatars.githubusercontent.com/u/15976103",
        "name": "yihong",
        "repo": {
            "description": "2022 gogogo",
            "name": "2022",
            "url": "https://github.com/yihong0618/2022"
        },
        "sponsorUrl": null,
        "url": "https://github.com/yihong0618",
        "username": "yihong0618"
    },
    {
        "avatar": "https://avatars.githubusercontent.com/u/16267321",
        "name": "Zeeshan Ahmad",
        "repo": {
            "description": "Learn regex the easy way",
            "name": "learn-regex",
            "url": "https://github.com/ziishaned/learn-regex"
        },
        "sponsorUrl": null,
        "url": "https://github.com/ziishaned",
        "username": "ziishaned"
    },
    {
        "avatar": "https://avatars.githubusercontent.com/u/3384072",
        "name": "Marcus Noble",
        "repo": {
            "description": null,
            "name": "tweetsvg",
            "url": "https://github.com/AverageMarcus/tweetsvg"
        },
        "sponsorUrl": null,
        "url": "https://github.com/AverageMarcus",
        "username": "AverageMarcus"
    },
    {
        "avatar": "https://avatars.githubusercontent.com/u/15893072",
        "name": "Josh van Leeuwen",
        "repo": null,
        "sponsorUrl": null,
        "url": "https://github.com/JoshVanL",
        "username": "JoshVanL"
    },
    {
        "avatar": "https://avatars.githubusercontent.com/u/2946214",
        "name": "Joe Chen",
        "repo": {
            "description": "\u300aThe Way to Go\u300b\u4e2d\u6587\u8bd1\u672c\uff0c\u4e2d\u6587\u6b63\u5f0f\u540d\u300aGo \u5165\u95e8\u6307\u5357\u300b",
            "name": "the-way-to-go_ZH_CN",
            "url": "https://github.com/unknwon/the-way-to-go_ZH_CN"
        },
        "sponsorUrl": null,
        "url": "https://github.com/unknwon",
        "username": "unknwon"
    },
    {
        "avatar": "https://avatars.githubusercontent.com/u/110123",
        "name": "Paul Querna",
        "repo": {
            "description": "TOTP library for Go",
            "name": "otp",
            "url": "https://github.com/pquerna/otp"
        },
        "sponsorUrl": null,
        "url": "https://github.com/pquerna",
        "username": "pquerna"
    },
    {
        "avatar": "https://avatars.githubusercontent.com/u/931655",
        "name": "Suyeol Jeon",
        "repo": {
            "description": "\u2728 Super sweet syntactic sugar for Swift initializers",
            "name": "Then",
            "url": "https://github.com/devxoul/Then"
        },
        "sponsorUrl": null,
        "url": "https://github.com/devxoul",
        "username": "devxoul"
    }
]