[
    {
        "author": "ManimCommunity",
        "avatar": "https://github.com/ManimCommunity.png",
        "builtBy": [
            {
                "avatar": "https://avatars.githubusercontent.com/u/11601040",
                "href": "https://github.com/3b1b",
                "username": "3b1b"
            },
            {
                "avatar": "https://avatars.githubusercontent.com/u/1096704",
                "href": "https://github.com/leotrs",
                "username": "leotrs"
            },
            {
                "avatar": "https://avatars.githubusercontent.com/u/43117506",
                "href": "https://github.com/eulertour",
                "username": "eulertour"
            },
            {
                "avatar": "https://avatars.githubusercontent.com/u/49693820",
                "href": "https://github.com/naveen521kk",
                "username": "naveen521kk"
            },
            {
                "avatar": "https://avatars.githubusercontent.com/u/13440601",
                "href": "https://github.com/bhbr",
                "username": "bhbr"
            }
        ],
        "currentPeriodStars": 778,
        "description": "A community-maintained Python framework for creating mathematical animations.",
        "forks": 507,
        "fullname": "ManimCommunity/manim",
        "language": "Python",
        "languageColor": "#3572A5",
        "name": "manim",
        "stars": 5783,
        "url": "https://github.com/ManimCommunity/manim"
    },
    {
        "author": "public-apis",
        "avatar": "https://github.com/public-apis.png",
        "builtBy": [
            {
                "avatar": "https://avatars.githubusercontent.com/u/15134885",
                "href": "https://github.com/davemachado",
                "username": "davemachado"
            },
            {
                "avatar": "https://avatars.githubusercontent.com/u/50463866",
                "href": "https://github.com/matheusfelipeog",
                "username": "matheusfelipeog"
            },
            {
                "avatar": "https://avatars.githubusercontent.com/u/246103",
                "href": "https://github.com/jbrooksuk",
                "username": "jbrooksuk"
            },
            {
                "avatar": "https://avatars.githubusercontent.com/u/354085",
                "href": "https://github.com/mikestreety",
                "username": "mikestreety"
            },
            {
                "avatar": "https://avatars.githubusercontent.com/u/1914165",
                "href": "https://github.com/marekdano",
                "username": "marekdano"
            }
        ],
        "currentPeriodStars": 1486,
        "description": "A collective list of free APIs",
        "forks": 17251,
        "fullname": "public-apis/public-apis",
        "language": "Python",
        "languageColor": "#3572A5",
        "name": "public-apis",
        "stars": 151606,
        "url": "https://github.com/public-apis/public-apis"
    },
    {
        "author": "papers-we-love",
        "avatar": "https://github.com/papers-we-love.png",
        "builtBy": [
            {
                "avatar": "https://avatars.githubusercontent.com/u/202820",
                "href": "https://github.com/zeeshanlakhani",
                "username": "zeeshanlakhani"
            },
            {
                "avatar": "https://avatars.githubusercontent.com/u/215030",
                "href": "https://github.com/DarrenN",
                "username": "DarrenN"
            },
            {
                "avatar": "https://avatars.githubusercontent.com/u/183600",
                "href": "https://github.com/jeremyheiler",
                "username": "jeremyheiler"
            },
            {
                "avatar": "https://avatars.githubusercontent.com/u/79253",
                "href": "https://github.com/newsomc",
                "username": "newsomc"
            },
            {
                "avatar": "https://avatars.githubusercontent.com/u/420078",
                "href": "https://github.com/bowmanb",
                "username": "bowmanb"
            }
        ],
        "currentPeriodStars": 356,
        "description": "Papers from the computer science community to read and discuss.",
        "forks": 4129,
        "fullname": "papers-we-love/papers-we-love",
        "language": "Shell",
        "languageColor": "#89e051",
        "name": "papers-we-love",
        "stars": 47434,
        "url": "https://github.com/papers-we-love/papers-we-love"
    },
    {
        "author": "babysor",
        "avatar": "https://github.com/babysor.png",
        "builtBy": [
            {
                "avatar": "https://avatars.githubusercontent.com/u/7423248",
                "href": "https://github.com/babysor",
                "username": "babysor"
            },
            {
                "avatar": "https://avatars.githubusercontent.com/u/12797292",
                "href": "https://github.com/oceanarium",
                "username": "oceanarium"
            }
        ],
        "currentPeriodStars": 719,
        "description": "\ud83d\ude80AI\u62df\u58f0: 5\u79d2\u5185\u514b\u9686\u60a8\u7684\u58f0\u97f3\u5e76\u751f\u6210\u4efb\u610f\u8bed\u97f3\u5185\u5bb9 Clone a voice in 5 seconds to generate arbitrary speech in real-time",
        "forks": 160,
        "fullname": "babysor/Realtime-Voice-Clone-Chinese",
        "language": "Python",
        "languageColor": "#3572A5",
        "name": "Realtime-Voice-Clone-Chinese",
        "stars": 1878,
        "url": "https://github.com/babysor/Realtime-Voice-Clone-Chinese"
    },
    {
        "author": "tenacityteam",
        "avatar": "https://github.com/tenacityteam.png",
        "builtBy": [
            {
                "avatar": "https://avatars.githubusercontent.com/u/11670369",
                "href": "https://github.com/Paul-Licameli",
                "username": "Paul-Licameli"
            },
            {
                "avatar": "https://avatars.githubusercontent.com/u/1621525",
                "href": "https://github.com/JamesCrook",
                "username": "JamesCrook"
            },
            {
                "avatar": "https://avatars.githubusercontent.com/u/7347848",
                "href": "https://github.com/lllucius",
                "username": "lllucius"
            },
            {
                "avatar": "https://avatars.githubusercontent.com/u/11681097",
                "href": "https://github.com/SteveDaulton",
                "username": "SteveDaulton"
            },
            {
                "avatar": "https://avatars.githubusercontent.com/u/11887021",
                "href": "https://github.com/DavidBailes",
                "username": "DavidBailes"
            }
        ],
        "currentPeriodStars": 519,
        "description": "Tenacity is an easy-to-use, privacy-friendly, FLOSS, cross-platform multi-track audio editor/recorder for Windows, macOS, Linux and other operating systems. Contributions welcome!",
        "forks": 253,
        "fullname": "tenacityteam/tenacity",
        "language": "C++",
        "languageColor": "#f34b7d",
        "name": "tenacity",
        "stars": 6007,
        "url": "https://github.com/tenacityteam/tenacity"
    },
    {
        "author": "flutter",
        "avatar": "https://github.com/flutter.png",
        "builtBy": [
            {
                "avatar": "https://avatars.githubusercontent.com/u/42042535",
                "href": "https://github.com/engine-flutter-autoroll",
                "username": "engine-flutter-autoroll"
            },
            {
                "avatar": "https://avatars.githubusercontent.com/u/112007",
                "href": "https://github.com/abarth",
                "username": "abarth"
            },
            {
                "avatar": "https://avatars.githubusercontent.com/u/551196",
                "href": "https://github.com/Hixie",
                "username": "Hixie"
            },
            {
                "avatar": "https://avatars.githubusercontent.com/u/8975114",
                "href": "https://github.com/jonahwilliams",
                "username": "jonahwilliams"
            },
            {
                "avatar": "https://avatars.githubusercontent.com/u/1377460",
                "href": "https://github.com/HansMuller",
                "username": "HansMuller"
            }
        ],
        "currentPeriodStars": 364,
        "description": "Flutter makes it easy and fast to build beautiful apps for mobile and beyond.",
        "forks": 18389,
        "fullname": "flutter/flutter",
        "language": "Dart",
        "languageColor": "#00B4AB",
        "name": "flutter",
        "stars": 128161,
        "url": "https://github.com/flutter/flutter"
    },
    {
        "author": "praetorian-inc",
        "avatar": "https://github.com/praetorian-inc.png",
        "builtBy": [
            {
                "avatar": "https://avatars.githubusercontent.com/u/58926491",
                "href": "https://github.com/praetorian-harry",
                "username": "praetorian-harry"
            },
            {
                "avatar": "https://avatars.githubusercontent.com/u/41651270",
                "href": "https://github.com/jessesomerville",
                "username": "jessesomerville"
            },
            {
                "avatar": "https://avatars.githubusercontent.com/u/42022383",
                "href": "https://github.com/trumankain",
                "username": "trumankain"
            }
        ],
        "currentPeriodStars": 610,
        "description": "A static analysis tool for securing Go code",
        "forks": 39,
        "fullname": "praetorian-inc/gokart",
        "language": "Go",
        "languageColor": "#00ADD8",
        "name": "gokart",
        "stars": 1170,
        "url": "https://github.com/praetorian-inc/gokart"
    },
    {
        "author": "Lux-AI-Challenge",
        "avatar": "https://github.com/Lux-AI-Challenge.png",
        "builtBy": [
            {
                "avatar": "https://avatars.githubusercontent.com/u/35373228",
                "href": "https://github.com/StoneT2000",
                "username": "StoneT2000"
            },
            {
                "avatar": "https://avatars.githubusercontent.com/u/3527954",
                "href": "https://github.com/holypegasus",
                "username": "holypegasus"
            },
            {
                "avatar": "https://avatars.githubusercontent.com/u/28755321",
                "href": "https://github.com/LittleAlvinMaker",
                "username": "LittleAlvinMaker"
            },
            {
                "avatar": "https://avatars.githubusercontent.com/u/6512637",
                "href": "https://github.com/djkeyes",
                "username": "djkeyes"
            },
            {
                "avatar": "https://avatars.githubusercontent.com/u/42013493",
                "href": "https://github.com/Desperationis",
                "username": "Desperationis"
            }
        ],
        "currentPeriodStars": 105,
        "description": "Home to the design and engine of the Lux AI Challenge Season 1",
        "forks": 23,
        "fullname": "Lux-AI-Challenge/Lux-Design-2021",
        "language": "C++",
        "languageColor": "#f34b7d",
        "name": "Lux-Design-2021",
        "stars": 164,
        "url": "https://github.com/Lux-AI-Challenge/Lux-Design-2021"
    },
    {
        "author": "go-sql-driver",
        "avatar": "https://github.com/go-sql-driver.png",
        "builtBy": [
            {
                "avatar": "https://avatars.githubusercontent.com/u/944947",
                "href": "https://github.com/julienschmidt",
                "username": "julienschmidt"
            },
            {
                "avatar": "https://avatars.githubusercontent.com/u/1011413",
                "href": "https://github.com/arnehormann",
                "username": "arnehormann"
            },
            {
                "avatar": "https://avatars.githubusercontent.com/u/199592",
                "href": "https://github.com/methane",
                "username": "methane"
            },
            {
                "avatar": "https://avatars.githubusercontent.com/u/1157344",
                "href": "https://github.com/shogo82148",
                "username": "shogo82148"
            },
            {
                "avatar": "https://avatars.githubusercontent.com/u/1209733",
                "href": "https://github.com/cxmcc",
                "username": "cxmcc"
            }
        ],
        "currentPeriodStars": 150,
        "description": "Go MySQL Driver is a MySQL driver for Go's (golang) database/sql package",
        "forks": 1981,
        "fullname": "go-sql-driver/mysql",
        "language": "Go",
        "languageColor": "#00ADD8",
        "name": "mysql",
        "stars": 11353,
        "url": "https://github.com/go-sql-driver/mysql"
    },
    {
        "author": "NvChad",
        "avatar": "https://github.com/NvChad.png",
        "builtBy": [
            {
                "avatar": "https://avatars.githubusercontent.com/u/59060246",
                "href": "https://github.com/siduck76",
                "username": "siduck76"
            },
            {
                "avatar": "https://avatars.githubusercontent.com/u/32216346",
                "href": "https://github.com/Akianonymus",
                "username": "Akianonymus"
            },
            {
                "avatar": "https://avatars.githubusercontent.com/u/83629316",
                "href": "https://github.com/ashincoder",
                "username": "ashincoder"
            },
            {
                "avatar": "https://avatars.githubusercontent.com/u/52706578",
                "href": "https://github.com/Vanderscycle",
                "username": "Vanderscycle"
            },
            {
                "avatar": "https://avatars.githubusercontent.com/u/3367398",
                "href": "https://github.com/G-Rowell",
                "username": "G-Rowell"
            }
        ],
        "currentPeriodStars": 877,
        "description": "An attempt to make neovim cli as functional as an IDE while being very beautiful , blazing fast.",
        "forks": 246,
        "fullname": "NvChad/NvChad",
        "language": "Lua",
        "languageColor": "#000080",
        "name": "NvChad",
        "stars": 5520,
        "url": "https://github.com/NvChad/NvChad"
    },
    {
        "author": "LiveOverflow",
        "avatar": "https://github.com/LiveOverflow.png",
        "builtBy": [
            {
                "avatar": "https://avatars.githubusercontent.com/u/12161158",
                "href": "https://github.com/LiveOverflow",
                "username": "LiveOverflow"
            }
        ],
        "currentPeriodStars": 68,
        "description": "a CTF web challenge about making screenshots",
        "forks": 14,
        "fullname": "LiveOverflow/ctf-screenshotter",
        "language": "Python",
        "languageColor": "#3572A5",
        "name": "ctf-screenshotter",
        "stars": 110,
        "url": "https://github.com/LiveOverflow/ctf-screenshotter"
    },
    {
        "author": "wuyouzhuguli",
        "avatar": "https://github.com/wuyouzhuguli.png",
        "builtBy": [
            {
                "avatar": "https://avatars.githubusercontent.com/u/16661027",
                "href": "https://github.com/wuyouzhuguli",
                "username": "wuyouzhuguli"
            },
            {
                "avatar": "https://avatars.githubusercontent.com/u/26996795",
                "href": "https://github.com/xianqiangzhao",
                "username": "xianqiangzhao"
            }
        ],
        "currentPeriodStars": 90,
        "description": "\u5faa\u5e8f\u6e10\u8fdb\uff0c\u5b66\u4e60Spring Boot\u3001Spring Boot & Shiro\u3001Spring Batch\u3001Spring Cloud\u3001Spring Cloud Alibaba\u3001Spring Security & Spring Security OAuth2\uff0c\u535a\u5ba2Spring\u7cfb\u5217\u6e90\u7801\uff1ahttps://mrbird.cc",
        "forks": 6406,
        "fullname": "wuyouzhuguli/SpringAll",
        "language": "Java",
        "languageColor": "#b07219",
        "name": "SpringAll",
        "stars": 21382,
        "url": "https://github.com/wuyouzhuguli/SpringAll"
    },
    {
        "author": "DIGITALCRIMINAL",
        "avatar": "https://github.com/DIGITALCRIMINAL.png",
        "builtBy": [
            {
                "avatar": "https://avatars.githubusercontent.com/u/21285176",
                "href": "https://github.com/DIGITALCRIMINAL",
                "username": "DIGITALCRIMINAL"
            },
            {
                "avatar": "https://avatars.githubusercontent.com/u/62782488",
                "href": "https://github.com/aboredpervert",
                "username": "aboredpervert"
            },
            {
                "avatar": "https://avatars.githubusercontent.com/u/62401845",
                "href": "https://github.com/ecchiecchi0",
                "username": "ecchiecchi0"
            },
            {
                "avatar": "https://avatars.githubusercontent.com/u/56813399",
                "href": "https://github.com/helopy",
                "username": "helopy"
            },
            {
                "avatar": "https://avatars.githubusercontent.com/u/56203079",
                "href": "https://github.com/banillasolt",
                "username": "banillasolt"
            }
        ],
        "currentPeriodStars": 67,
        "description": "Scrape all the media from an OnlyFans account - Updated regularly",
        "forks": 307,
        "fullname": "DIGITALCRIMINAL/OnlyFans",
        "language": "Python",
        "languageColor": "#3572A5",
        "name": "OnlyFans",
        "stars": 1977,
        "url": "https://github.com/DIGITALCRIMINAL/OnlyFans"
    },
    {
        "author": "swisskyrepo",
        "avatar": "https://github.com/swisskyrepo.png",
        "builtBy": [
            {
                "avatar": "https://avatars.githubusercontent.com/u/12152583",
                "href": "https://github.com/swisskyrepo",
                "username": "swisskyrepo"
            },
            {
                "avatar": "https://avatars.githubusercontent.com/u/16578570",
                "href": "https://github.com/noraj",
                "username": "noraj"
            },
            {
                "avatar": "https://avatars.githubusercontent.com/u/25560738",
                "href": "https://github.com/cyber-niz",
                "username": "cyber-niz"
            },
            {
                "avatar": "https://avatars.githubusercontent.com/u/214154",
                "href": "https://github.com/lanjelot",
                "username": "lanjelot"
            },
            {
                "avatar": "https://avatars.githubusercontent.com/u/15129756",
                "href": "https://github.com/marcan2020",
                "username": "marcan2020"
            }
        ],
        "currentPeriodStars": 382,
        "description": "A list of useful payloads and bypass for Web Application Security and Pentest/CTF",
        "forks": 8059,
        "fullname": "swisskyrepo/PayloadsAllTheThings",
        "language": "Python",
        "languageColor": "#3572A5",
        "name": "PayloadsAllTheThings",
        "stars": 29374,
        "url": "https://github.com/swisskyrepo/PayloadsAllTheThings"
    },
    {
        "author": "vandadnp",
        "avatar": "https://github.com/vandadnp.png",
        "builtBy": [
            {
                "avatar": "https://avatars.githubusercontent.com/u/759524",
                "href": "https://github.com/vandadnp",
                "username": "vandadnp"
            }
        ],
        "currentPeriodStars": 121,
        "description": "A Collection of Flutter and Dart Tips and Tricks",
        "forks": 77,
        "fullname": "vandadnp/flutter-tips-and-tricks",
        "language": "Dart",
        "languageColor": "#00B4AB",
        "name": "flutter-tips-and-tricks",
        "stars": 673,
        "url": "https://github.com/vandadnp/flutter-tips-and-tricks"
    },
    {
        "author": "spring-projects",
        "avatar": "https://github.com/spring-projects.png",
        "builtBy": [
            {
                "avatar": "https://avatars.githubusercontent.com/u/10884212",
                "href": "https://github.com/jgrandja",
                "username": "jgrandja"
            },
            {
                "avatar": "https://avatars.githubusercontent.com/u/5248162",
                "href": "https://github.com/sjohnr",
                "username": "sjohnr"
            },
            {
                "avatar": "https://avatars.githubusercontent.com/u/5676779",
                "href": "https://github.com/Kehrlann",
                "username": "Kehrlann"
            },
            {
                "avatar": "https://avatars.githubusercontent.com/u/362503",
                "href": "https://github.com/rwinch",
                "username": "rwinch"
            },
            {
                "avatar": "https://avatars.githubusercontent.com/u/12255420",
                "href": "https://github.com/anoopgarlapati",
                "username": "anoopgarlapati"
            }
        ],
        "currentPeriodStars": 155,
        "description": "A community-driven project led by the Spring Security team and is focused on delivering Authorization Server support to the Spring community",
        "forks": 443,
        "fullname": "spring-projects/spring-authorization-server",
        "language": "Java",
        "languageColor": "#b07219",
        "name": "spring-authorization-server",
        "stars": 2491,
        "url": "https://github.com/spring-projects/spring-authorization-server"
    },
    {
        "author": "open-metadata",
        "avatar": "https://github.com/open-metadata.png",
        "builtBy": [
            {
                "avatar": "https://avatars.githubusercontent.com/u/1417689",
                "href": "https://github.com/sureshms",
                "username": "sureshms"
            },
            {
                "avatar": "https://avatars.githubusercontent.com/u/40225091",
                "href": "https://github.com/ayush-shah",
                "username": "ayush-shah"
            },
            {
                "avatar": "https://avatars.githubusercontent.com/u/86726556",
                "href": "https://github.com/darth-coder00",
                "username": "darth-coder00"
            },
            {
                "avatar": "https://avatars.githubusercontent.com/u/59080942",
                "href": "https://github.com/Sachin-chaurasiya",
                "username": "Sachin-chaurasiya"
            },
            {
                "avatar": "https://avatars.githubusercontent.com/u/6761317",
                "href": "https://github.com/shahsank3t",
                "username": "shahsank3t"
            }
        ],
        "currentPeriodStars": 126,
        "description": "Open Standard for Metadata. A Single place to Discover, Collaborate and Get your data right.",
        "forks": 12,
        "fullname": "open-metadata/OpenMetadata",
        "language": "Java",
        "languageColor": "#b07219",
        "name": "OpenMetadata",
        "stars": 244,
        "url": "https://github.com/open-metadata/OpenMetadata"
    },
    {
        "author": "ANYbotics",
        "avatar": "https://github.com/ANYbotics.png",
        "builtBy": [
            {
                "avatar": "https://avatars.githubusercontent.com/u/2306025",
                "href": "https://github.com/pfankhauser",
                "username": "pfankhauser"
            },
            {
                "avatar": "https://avatars.githubusercontent.com/u/2513562",
                "href": "https://github.com/martiwer",
                "username": "martiwer"
            },
            {
                "avatar": "https://avatars.githubusercontent.com/u/3808643",
                "href": "https://github.com/remod",
                "username": "remod"
            },
            {
                "avatar": "https://avatars.githubusercontent.com/u/12872984",
                "href": "https://github.com/mktk1117",
                "username": "mktk1117"
            },
            {
                "avatar": "https://avatars.githubusercontent.com/u/3610764",
                "href": "https://github.com/samuelba",
                "username": "samuelba"
            }
        ],
        "currentPeriodStars": 42,
        "description": "Universal grid map library for mobile robotic mapping",
        "forks": 563,
        "fullname": "ANYbotics/grid_map",
        "language": "C++",
        "languageColor": "#f34b7d",
        "name": "grid_map",
        "stars": 1360,
        "url": "https://github.com/ANYbotics/grid_map"
    },
    {
        "author": "rcmaehl",
        "avatar": "https://github.com/rcmaehl.png",
        "builtBy": [
            {
                "avatar": "https://avatars.githubusercontent.com/u/716581",
                "href": "https://github.com/rcmaehl",
                "username": "rcmaehl"
            },
            {
                "avatar": "https://avatars.githubusercontent.com/u/45581170",
                "href": "https://github.com/micwoj92",
                "username": "micwoj92"
            },
            {
                "avatar": "https://avatars.githubusercontent.com/u/62497891",
                "href": "https://github.com/Oleg-Chashko",
                "username": "Oleg-Chashko"
            },
            {
                "avatar": "https://avatars.githubusercontent.com/u/11089482",
                "href": "https://github.com/mlipok",
                "username": "mlipok"
            },
            {
                "avatar": "https://avatars.githubusercontent.com/u/86588462",
                "href": "https://github.com/Qazy147",
                "username": "Qazy147"
            }
        ],
        "currentPeriodStars": 62,
        "description": "Detection Script to help identify why your PC is not Windows 11 Release Ready",
        "forks": 366,
        "fullname": "rcmaehl/WhyNotWin11",
        "language": "AutoIt",
        "languageColor": "#1C3552",
        "name": "WhyNotWin11",
        "stars": 5041,
        "url": "https://github.com/rcmaehl/WhyNotWin11"
    },
    {
        "author": "honzaap",
        "avatar": "https://github.com/honzaap.png",
        "builtBy": [
            {
                "avatar": "https://avatars.githubusercontent.com/u/58147774",
                "href": "https://github.com/honzaap",
                "username": "honzaap"
            },
            {
                "avatar": "https://avatars.githubusercontent.com/u/67814205",
                "href": "https://github.com/dineshkumar12004",
                "username": "dineshkumar12004"
            },
            {
                "avatar": "https://avatars.githubusercontent.com/u/28998404",
                "href": "https://github.com/Gbd199",
                "username": "Gbd199"
            }
        ],
        "currentPeriodStars": 293,
        "description": "A system design tool that allows you to simulate data flow of distributed systems.",
        "forks": 55,
        "fullname": "honzaap/Systemizer",
        "language": "TypeScript",
        "languageColor": "#2b7489",
        "name": "Systemizer",
        "stars": 802,
        "url": "https://github.com/honzaap/Systemizer"
    },
    {
        "author": "labmlai",
        "avatar": "https://github.com/labmlai.png",
        "builtBy": [
            {
                "avatar": "https://avatars.githubusercontent.com/u/81152",
                "href": "https://github.com/vpj",
                "username": "vpj"
            },
            {
                "avatar": "https://avatars.githubusercontent.com/u/78550290",
                "href": "https://github.com/KeshSam",
                "username": "KeshSam"
            },
            {
                "avatar": "https://avatars.githubusercontent.com/u/77142935",
                "href": "https://github.com/sachdevkartik",
                "username": "sachdevkartik"
            },
            {
                "avatar": "https://avatars.githubusercontent.com/u/18068305",
                "href": "https://github.com/shakedbr",
                "username": "shakedbr"
            },
            {
                "avatar": "https://avatars.githubusercontent.com/u/65212523",
                "href": "https://github.com/Aarsh2001",
                "username": "Aarsh2001"
            }
        ],
        "currentPeriodStars": 334,
        "description": "\ud83e\uddd1\u200d\ud83c\udfeb Implementations/tutorials of deep learning papers with side-by-side notes \ud83d\udcdd; including transformers (original, xl, switch, feedback, vit), optimizers (adam, radam, adabelief), gans(dcgan, cyclegan, stylegan2), \ud83c\udfae reinforcement learning (ppo, dqn), capsnet, distillation, etc. \ud83e\udde0",
        "forks": 261,
        "fullname": "labmlai/annotated_deep_learning_paper_implementations",
        "language": "Jupyter Notebook",
        "languageColor": "#DA5B0B",
        "name": "annotated_deep_learning_paper_implementations",
        "stars": 4483,
        "url": "https://github.com/labmlai/annotated_deep_learning_paper_implementations"
    },
    {
        "author": "samuelmarina",
        "avatar": "https://github.com/samuelmarina.png",
        "builtBy": [
            {
                "avatar": "https://avatars.githubusercontent.com/u/59328925",
                "href": "https://github.com/samuelmarina",
                "username": "samuelmarina"
            },
            {
                "avatar": "https://avatars.githubusercontent.com/u/22660277",
                "href": "https://github.com/lamergameryt",
                "username": "lamergameryt"
            },
            {
                "avatar": "https://avatars.githubusercontent.com/u/24570483",
                "href": "https://github.com/gingerbenw",
                "username": "gingerbenw"
            },
            {
                "avatar": "https://avatars.githubusercontent.com/u/59015168",
                "href": "https://github.com/HyperBeasty",
                "username": "HyperBeasty"
            },
            {
                "avatar": "https://avatars.githubusercontent.com/u/59713767",
                "href": "https://github.com/SJM96",
                "username": "SJM96"
            }
        ],
        "currentPeriodStars": 336,
        "description": "Is a number even?",
        "forks": 183,
        "fullname": "samuelmarina/is-even",
        "language": null,
        "languageColor": null,
        "name": "is-even",
        "stars": 932,
        "url": "https://github.com/samuelmarina/is-even"
    },
    {
        "author": "SerenityOS",
        "avatar": "https://github.com/SerenityOS.png",
        "builtBy": [
            {
                "avatar": "https://avatars.githubusercontent.com/u/5954907",
                "href": "https://github.com/awesomekling",
                "username": "awesomekling"
            },
            {
                "avatar": "https://avatars.githubusercontent.com/u/19366641",
                "href": "https://github.com/linusg",
                "username": "linusg"
            },
            {
                "avatar": "https://avatars.githubusercontent.com/u/14001776",
                "href": "https://github.com/alimpfard",
                "username": "alimpfard"
            },
            {
                "avatar": "https://avatars.githubusercontent.com/u/388571",
                "href": "https://github.com/gunnarbeutner",
                "username": "gunnarbeutner"
            },
            {
                "avatar": "https://avatars.githubusercontent.com/u/1212",
                "href": "https://github.com/bgianfo",
                "username": "bgianfo"
            }
        ],
        "currentPeriodStars": 298,
        "description": "The Serenity Operating System \ud83d\udc1e",
        "forks": 1512,
        "fullname": "SerenityOS/serenity",
        "language": "C++",
        "languageColor": "#f34b7d",
        "name": "serenity",
        "stars": 14886,
        "url": "https://github.com/SerenityOS/serenity"
    },
    {
        "author": "armosec",
        "avatar": "https://github.com/armosec.png",
        "builtBy": [
            {
                "avatar": "https://avatars.githubusercontent.com/u/59160382",
                "href": "https://github.com/BenHirschbergCa",
                "username": "BenHirschbergCa"
            },
            {
                "avatar": "https://avatars.githubusercontent.com/u/64066841",
                "href": "https://github.com/dwertent",
                "username": "dwertent"
            },
            {
                "avatar": "https://avatars.githubusercontent.com/u/84905812",
                "href": "https://github.com/Daniel-GrunbergerCA",
                "username": "Daniel-GrunbergerCA"
            }
        ],
        "currentPeriodStars": 291,
        "description": "kubescape is the first tool for testing if Kubernetes is deployed securely as defined in Kubernetes Hardening Guidance by to NSA and CISA (https://www.nsa.gov/News-Features/Feature-Stories/Article-View/Article/2716980/nsa-cisa-release-kubernetes-hardening-guidance/)",
        "forks": 15,
        "fullname": "armosec/kubescape",
        "language": "Go",
        "languageColor": "#00ADD8",
        "name": "kubescape",
        "stars": 367,
        "url": "https://github.com/armosec/kubescape"
    },
    {
        "author": "visenger",
        "avatar": "https://github.com/visenger.png",
        "builtBy": [
            {
                "avatar": "https://avatars.githubusercontent.com/u/2014749",
                "href": "https://github.com/visenger",
                "username": "visenger"
            },
            {
                "avatar": "https://avatars.githubusercontent.com/u/18099827",
                "href": "https://github.com/stefanodallapalma",
                "username": "stefanodallapalma"
            },
            {
                "avatar": "https://avatars.githubusercontent.com/u/25026003",
                "href": "https://github.com/naiiytom",
                "username": "naiiytom"
            },
            {
                "avatar": "https://avatars.githubusercontent.com/u/128572",
                "href": "https://github.com/bact",
                "username": "bact"
            },
            {
                "avatar": "https://avatars.githubusercontent.com/u/8433587",
                "href": "https://github.com/spekulatius",
                "username": "spekulatius"
            }
        ],
        "currentPeriodStars": 122,
        "description": "A curated list of references for MLOps",
        "forks": 817,
        "fullname": "visenger/awesome-mlops",
        "language": null,
        "languageColor": null,
        "name": "awesome-mlops",
        "stars": 5724,
        "url": "https://github.com/visenger/awesome-mlops"
    }
]